MANIFEST.in
README.rst
setup.py
logstash_handler/__init__.py
logstash_handler.egg-info/PKG-INFO
logstash_handler.egg-info/SOURCES.txt
logstash_handler.egg-info/dependency_links.txt
logstash_handler.egg-info/requires.txt
logstash_handler.egg-info/top_level.txt
logstash_handler.egg-info/zip-safe