Metadata-Version: 1.1
Name: logstash-handler
Version: 0.1.0
Summary: Log handler meant for logstash
Home-page: https://github.com/klynch/python-logstash-handler
Author: Kevin Lynch
Author-email: klynch@drakontas.com
License: MIT
Platform: UNKNOWN
Classifier: Development Status :: 5 - Production/Stable
Classifier: Intended Audience :: Developers
Classifier: License :: OSI Approved :: MIT License
Classifier: Natural Language :: English
Classifier: Programming Language :: Python
Classifier: Programming Language :: Python :: 3
